{
  "portfolios": {
    "S&P 500 MultiFactor Sector Rotation Model": {
      "total_return": 0.016193,
      "sharpe": 0.7054,
      "volatility": 0.088741,
      "max_drawdown": -0.028595,
      "sortino": 1.3911,
      "correlations": {
        "CSPX.L": 0.8634
      },
      "beta": 0.6518,
      "beta_vs": "CSPX.L",
      "up_capture": 0.6056,
      "down_capture": 0.6358,
      "capture_vs": "CSPX.L"
    },
    "iShares S&P 500 Equal Weight UCITS ETF": {
      "total_return": 0.026396,
      "sharpe": 1.0876,
      "volatility": 0.091341,
      "max_drawdown": -0.03057,
      "sortino": 1.8351,
      "correlations": {
        "CSPX.L": 0.6878
      },
      "beta": 0.5345,
      "beta_vs": "CSPX.L",
      "up_capture": 0.5968,
      "down_capture": 0.5671,
      "capture_vs": "CSPX.L"
    }
  },
  "benchmarks": {
    "CSPX.L": {
      "total_return": 0.035526,
      "sharpe": 1.1287,
      "volatility": 0.119278,
      "max_drawdown": -0.047622,
      "sortino": 2.1027,
      "beta": 1.0,
      "up_capture": 1.0,
      "down_capture": 1.0,
      "beta_vs": "",
      "capture_vs": ""
    }
  }
}