{
  "portfolios": {
    "S&P 500 MultiFactor Sector Rotation Model": {
      "total_return": 0.011635,
      "sharpe": 0.4742,
      "volatility": 0.087999,
      "max_drawdown": -0.028595,
      "sortino": 0.9148,
      "correlations": {
        "CSPX.L": 0.8709
      },
      "beta": 0.6563,
      "beta_vs": "CSPX.L",
      "up_capture": 0.6228,
      "down_capture": 0.6376,
      "capture_vs": "CSPX.L"
    },
    "iShares S&P 500 Equal Weight UCITS ETF": {
      "total_return": 0.035109,
      "sharpe": 1.2362,
      "volatility": 0.095031,
      "max_drawdown": -0.03057,
      "sortino": 2.1199,
      "correlations": {
        "CSPX.L": 0.6712
      },
      "beta": 0.5462,
      "beta_vs": "CSPX.L",
      "up_capture": 0.6228,
      "down_capture": 0.5236,
      "capture_vs": "CSPX.L"
    }
  },
  "benchmarks": {
    "CSPX.L": {
      "total_return": 0.023293,
      "sharpe": 0.696,
      "volatility": 0.118319,
      "max_drawdown": -0.047622,
      "sortino": 1.2743,
      "beta": 1.0,
      "up_capture": 1.0,
      "down_capture": 1.0,
      "beta_vs": "",
      "capture_vs": ""
    }
  }
}